AUTHORS.md
LICENSE
README.md
pyproject.toml
setup.py
bigraph/__init__.py
bigraph/bigraph.py
bigraph/cli.py
bigraph/history.py
bigraph/metabolism.py
bigraph/modulo.py
bigraph/parse.py
bigraphs.egg-info/PKG-INFO
bigraphs.egg-info/SOURCES.txt
bigraphs.egg-info/dependency_links.txt
bigraphs.egg-info/entry_points.txt
bigraphs.egg-info/requires.txt
bigraphs.egg-info/top_level.txt